README.rst
setup.py
SuperBoL.egg-info/PKG-INFO
SuperBoL.egg-info/SOURCES.txt
SuperBoL.egg-info/dependency_links.txt
SuperBoL.egg-info/requires.txt
SuperBoL.egg-info/top_level.txt
superbol/__init__.py
superbol/bc_polynomial.py
superbol/constants.py
superbol/fbol.py
superbol/fit_blackbody.py
superbol/luminosity.py
superbol/mag2flux.py
superbol/planck.py
superbol/sn.py
superbol/data/sn_data.h5