Metadata-Version: 1.1
Name: SuperBoL
Version: 0.3.4
Summary: Supernova Bolometric Lightcurves
Home-page: https://github.com/JALusk/SuperBoL
Author: Jeremy A. Lusk
Author-email: jeremy.lusk@gmail.com
License: MIT License
Platform: UNKNOWN
Classifier: Development Status :: 4 - Beta
Classifier: Intended Audience :: Science/Research
Classifier: License :: OSI Approved :: MIT License
Classifier: Natural Language :: English
Classifier: Programming Language :: Python :: 2.7
Classifier: Topic :: Scientific/Engineering :: Astronomy
